letsql-0.1.14.dist-info/METADATA
letsql-0.1.14.dist-info/WHEEL
letsql-0.1.14.dist-info/licenses/LICENSE
letsql/internal.py
letsql/config.py
letsql/__init__.py
letsql/selectors.py
letsql/_internal.abi3.so
letsql-0.1.14.dist-info/RECORD
