Metadata-Version: 2.4
Name: letsql
Version: 0.1.14
Classifier: Development Status :: 7 - Inactive
Requires-Dist: xorq==0.1.14 ; python_full_version >= '3.10' and python_full_version < '4.0'
License-File: LICENSE
Summary: Data processing library built on top of Ibis and DataFusion to write multi-engine data workflows.
Author-email: Hussain Sultan <hussain@letsql.com>
Maintainer-email: Dan Lovell <dan@letsql.com>, Daniel Mesejo <mesejo@letsql.com>
Requires-Python: >=3.10
